[
 {
  "amended_from": null,
  "amount_given_in": "Bank",
  "customer": "Mr Test",
  "docstatus": 0,
  "doctype": "Loan Details",
  "emi_amount": 93.33,
  "emi_schedule": [
   {
    "amount_paid": 0.0,
    "due_date": "2025-08-01",
    "emi_amount": 93.33,
    "installment_no": 1,
    "parent": "Mr Test-",
    "parentfield": "emi_schedule",
    "parenttype": "Loan Details",
    "payment_date": null,
    "remarks": null,
    "status": "Pending"
   },
   {
    "amount_paid": 0.0,
    "due_date": "2025-09-01",
    "emi_amount": 93.33,
    "installment_no": 2,
    "parent": "Mr Test-",
    "parentfield": "emi_schedule",
    "parenttype": "Loan Details",
    "payment_date": null,
    "remarks": null,
    "status": "Pending"
   },
   {
    "amount_paid": 0.0,
    "due_date": "2025-10-01",
    "emi_amount": 93.33,
    "installment_no": 3,
    "parent": "Mr Test-",
    "parentfield": "emi_schedule",
    "parenttype": "Loan Details",
    "payment_date": null,
    "remarks": null,
    "status": "Pending"
   },
   {
    "amount_paid": 0.0,
    "due_date": "2025-11-01",
    "emi_amount": 93.33,
    "installment_no": 4,
    "parent": "Mr Test-",
    "parentfield": "emi_schedule",
    "parenttype": "Loan Details",
    "payment_date": null,
    "remarks": null,
    "status": "Pending"
   },
   {
    "amount_paid": 0.0,
    "due_date": "2025-12-01",
    "emi_amount": 93.33,
    "installment_no": 5,
    "parent": "Mr Test-",
    "parentfield": "emi_schedule",
    "parenttype": "Loan Details",
    "payment_date": null,
    "remarks": null,
    "status": "Pending"
   },
   {
    "amount_paid": 0.0,
    "due_date": "2026-01-01",
    "emi_amount": 93.33,
    "installment_no": 6,
    "parent": "Mr Test-",
    "parentfield": "emi_schedule",
    "parenttype": "Loan Details",
    "payment_date": null,
    "remarks": null,
    "status": "Pending"
   },
   {
    "amount_paid": 0.0,
    "due_date": "2026-02-01",
    "emi_amount": 93.33,
    "installment_no": 7,
    "parent": "Mr Test-",
    "parentfield": "emi_schedule",
    "parenttype": "Loan Details",
    "payment_date": null,
    "remarks": null,
    "status": "Pending"
   },
   {
    "amount_paid": 0.0,
    "due_date": "2026-03-01",
    "emi_amount": 93.33,
    "installment_no": 8,
    "parent": "Mr Test-",
    "parentfield": "emi_schedule",
    "parenttype": "Loan Details",
    "payment_date": null,
    "remarks": null,
    "status": "Pending"
   },
   {
    "amount_paid": 0.0,
    "due_date": "2026-04-01",
    "emi_amount": 93.33,
    "installment_no": 9,
    "parent": "Mr Test-",
    "parentfield": "emi_schedule",
    "parenttype": "Loan Details",
    "payment_date": null,
    "remarks": null,
    "status": "Pending"
   },
   {
    "amount_paid": 0.0,
    "due_date": "2026-05-01",
    "emi_amount": 93.33,
    "installment_no": 10,
    "parent": "Mr Test-",
    "parentfield": "emi_schedule",
    "parenttype": "Loan Details",
    "payment_date": null,
    "remarks": null,
    "status": "Pending"
   },
   {
    "amount_paid": 0.0,
    "due_date": "2026-06-01",
    "emi_amount": 93.33,
    "installment_no": 11,
    "parent": "Mr Test-",
    "parentfield": "emi_schedule",
    "parenttype": "Loan Details",
    "payment_date": null,
    "remarks": null,
    "status": "Pending"
   },
   {
    "amount_paid": 0.0,
    "due_date": "2026-07-01",
    "emi_amount": 93.33,
    "installment_no": 12,
    "parent": "Mr Test-",
    "parentfield": "emi_schedule",
    "parenttype": "Loan Details",
    "payment_date": null,
    "remarks": null,
    "status": "Pending"
   }
  ],
  "guarantor": "",
  "interest_rate": 12.0,
  "loan_agreement_number": "123",
  "loan_amount": 1000.0,
  "loan_approval_date": "2025-07-19",
  "loan_duration": 12,
  "loan_end_date": "2026-08-01",
  "loan_purpose": null,
  "loan_start_date": "2025-08-01",
  "loan_type": "Flat Interest",
  "modified": "2025-07-19 20:50:39.234934",
  "name": "Mr Test-",
  "total_collection": "1120",
  "total_installments": 0
 }
]